gcp_cis/__init__.py
gcp_cis/gcp_cis_checks_iam.py
gcp_cis/gcp_cis_checks_logging_and_monitoring.py
gcp_cis/gcp_cis_checks_networking.py
gcp_cis/gcp_cis_checks_storage.py
gcp_cis/gcp_cis_checks_vms.py
gcp_cis/logger.py
gcp_cis-0.0.8.dist-info/LICENCE
gcp_cis-0.0.8.dist-info/METADATA
gcp_cis-0.0.8.dist-info/WHEEL
gcp_cis-0.0.8.dist-info/top_level.txt
gcp_cis-0.0.8.dist-info/RECORD
